{
  "schema": 2,
  "player_id": "chandler_phillips",
  "player_name": "Chandler Phillips",
  "wave": "all",
  "rating": {
    "skill": -0.281,
    "skill_overall": -0.309,
    "n_eff": 46.6,
    "n_course": 0.5,
    "course_rounds_played": 2
  },
  "expected": {
    "e_score": 69.78,
    "p10": 65.95,
    "p50": 69.38,
    "p90": 74.23,
    "sd": 3.3
  },
  "line": null,
  "bet": {
    "player_id": "chandler_phillips",
    "player_name": "Chandler Phillips",
    "wave": "all",
    "e_score": 69.78,
    "p10": 65.95,
    "p90": 74.23,
    "n_eff": 46.6,
    "has_line": false,
    "line": null,
    "side": "",
    "price": null,
    "model_prob": null,
    "novig_prob": null,
    "edge": null,
    "ev_per_unit": null,
    "kelly": null,
    "actionable": false
  },
  "distribution": {
    "counts": [
      5,
      17,
      38,
      127,
      260,
      591,
      926,
      1166,
      1242,
      1158,
      1079,
      870,
      688,
      563,
      420,
      270,
      215,
      137,
      105,
      54,
      26,
      26,
      7,
      10
    ],
    "edges": [
      60.24,
      61.2,
      62.16,
      63.11,
      64.07,
      65.03,
      65.99,
      66.95,
      67.9,
      68.86,
      69.82,
      70.78,
      71.74,
      72.69,
      73.65,
      74.61,
      75.57,
      76.53,
      77.48,
      78.44,
      79.4,
      80.36,
      81.32,
      82.27,
      83.23
    ]
  },
  "recent_rounds": [
    {
      "date": "2026-06-18 04:00:00",
      "course_id": "u_s_open",
      "round_num": 2,
      "to_par": 5.0
    },
    {
      "date": "2026-06-18 04:00:00",
      "course_id": "u_s_open",
      "round_num": 1,
      "to_par": 4.0
    },
    {
      "date": "2026-06-11 04:00:00",
      "course_id": "rbc_canadian_open",
      "round_num": 4,
      "to_par": -4.0
    },
    {
      "date": "2026-06-11 04:00:00",
      "course_id": "rbc_canadian_open",
      "round_num": 3,
      "to_par": -1.0
    },
    {
      "date": "2026-06-11 04:00:00",
      "course_id": "rbc_canadian_open",
      "round_num": 2,
      "to_par": -2.0
    },
    {
      "date": "2026-06-11 04:00:00",
      "course_id": "rbc_canadian_open",
      "round_num": 1,
      "to_par": -3.0
    },
    {
      "date": "2026-05-28 04:00:00",
      "course_id": "charles_schwab_challenge",
      "round_num": 2,
      "to_par": 0.0
    },
    {
      "date": "2026-05-28 04:00:00",
      "course_id": "charles_schwab_challenge",
      "round_num": 1,
      "to_par": 4.0
    },
    {
      "date": "2026-05-21 04:00:00",
      "course_id": "the_cj_cup_byron_nelson",
      "round_num": 2,
      "to_par": -1.0
    },
    {
      "date": "2026-05-21 04:00:00",
      "course_id": "the_cj_cup_byron_nelson",
      "round_num": 1,
      "to_par": -2.0
    }
  ]
}