{
  "schema": 3,
  "player_id": "lucas_herbert",
  "player_name": "Lucas Herbert",
  "wave": "all",
  "rating": {
    "skill": -0.112,
    "skill_overall": -0.071,
    "n_eff": 2.5,
    "n_course": 2.0,
    "course_rounds_played": 2
  },
  "expected": {
    "e_score": 73.88,
    "p10": 70.21,
    "p50": 73.53,
    "p90": 78.02,
    "sd": 3.07
  },
  "distribution": {
    "counts": [
      12,
      41,
      147,
      289,
      614,
      848,
      1183,
      1223,
      1218,
      1053,
      910,
      725,
      549,
      406,
      260,
      220,
      128,
      91,
      33,
      18,
      15,
      7,
      7,
      3
    ],
    "edges": [
      65.77,
      66.69,
      67.6,
      68.51,
      69.42,
      70.33,
      71.25,
      72.16,
      73.07,
      73.98,
      74.89,
      75.81,
      76.72,
      77.63,
      78.54,
      79.45,
      80.37,
      81.28,
      82.19,
      83.1,
      84.01,
      84.93,
      85.84,
      86.75,
      87.66
    ]
  },
  "recent_rounds": [
    {
      "date": "2026-06-18 04:00:00",
      "course_id": "u_s_open",
      "round_num": 1,
      "to_par": 4.0
    },
    {
      "date": "2026-06-18 04:00:00",
      "course_id": "u_s_open",
      "round_num": 2,
      "to_par": 2.0
    },
    {
      "date": "2025-07-17 04:00:00",
      "course_id": "the_open",
      "round_num": 1,
      "to_par": 3.0
    },
    {
      "date": "2025-07-17 04:00:00",
      "course_id": "the_open",
      "round_num": 2,
      "to_par": 1.0
    }
  ]
}