{
  "schema": 2,
  "player_id": "spencer_tibbits",
  "player_name": "Spencer Tibbits",
  "wave": "all",
  "rating": {
    "skill": -0.054,
    "skill_overall": -0.027,
    "n_eff": 3.9,
    "n_course": 3.9,
    "course_rounds_played": 4
  },
  "expected": {
    "e_score": 73.7,
    "p10": 69.72,
    "p50": 73.32,
    "p90": 78.23,
    "sd": 3.4
  },
  "line": null,
  "bet": {
    "player_id": "spencer_tibbits",
    "player_name": "Spencer Tibbits",
    "wave": "all",
    "e_score": 73.7,
    "p10": 69.72,
    "p90": 78.23,
    "n_eff": 3.9,
    "has_line": false,
    "line": null,
    "side": "",
    "price": null,
    "model_prob": null,
    "novig_prob": null,
    "edge": null,
    "ev_per_unit": null,
    "kelly": null,
    "actionable": false
  },
  "distribution": {
    "counts": [
      5,
      11,
      80,
      202,
      524,
      884,
      1193,
      1276,
      1335,
      1232,
      906,
      752,
      531,
      382,
      246,
      147,
      131,
      70,
      43,
      17,
      15,
      7,
      4,
      7
    ],
    "edges": [
      64.07,
      65.14,
      66.22,
      67.3,
      68.37,
      69.45,
      70.53,
      71.6,
      72.68,
      73.75,
      74.83,
      75.91,
      76.98,
      78.06,
      79.13,
      80.21,
      81.29,
      82.36,
      83.44,
      84.51,
      85.59,
      86.67,
      87.74,
      88.82,
      89.9
    ]
  },
  "recent_rounds": [
    {
      "date": "2026-06-18 04:00:00",
      "course_id": "u_s_open",
      "round_num": 1,
      "to_par": -2.0
    },
    {
      "date": "2026-06-18 04:00:00",
      "course_id": "u_s_open",
      "round_num": 2,
      "to_par": 4.0
    },
    {
      "date": "2026-06-18 04:00:00",
      "course_id": "u_s_open",
      "round_num": 3,
      "to_par": 6.0
    },
    {
      "date": "2026-06-18 04:00:00",
      "course_id": "u_s_open",
      "round_num": 4,
      "to_par": 3.0
    }
  ]
}