{
  "schema": 3,
  "disclaimer": "ACADEMIC EXERCISE \u2014 score prediction only. Not betting advice.",
  "generated_at": "2026-06-21T00:47:16.162370+00:00",
  "event_id": "401811952",
  "course_name": "U.S. Open",
  "round_num": 4,
  "par": 70,
  "predictions": [
    {
      "player_id": "scottie_scheffler",
      "player_name": "Scottie Scheffler",
      "wave": "all",
      "e_score": 71.26,
      "e_to_par": 1.26,
      "p10": 67.3,
      "p90": 75.89,
      "sd": 3.4,
      "n_eff": 56.8
    },
    {
      "player_id": "wyndham_clark",
      "player_name": "Wyndham Clark",
      "wave": "all",
      "e_score": 71.77,
      "e_to_par": 1.77,
      "p10": 67.34,
      "p90": 76.87,
      "sd": 3.8,
      "n_eff": 57.6
    },
    {
      "player_id": "matt_fitzpatrick",
      "player_name": "Matt Fitzpatrick",
      "wave": "all",
      "e_score": 71.91,
      "e_to_par": 1.91,
      "p10": 68.08,
      "p90": 76.24,
      "sd": 3.24,
      "n_eff": 55.6
    },
    {
      "player_id": "xander_schauffele",
      "player_name": "Xander Schauffele",
      "wave": "all",
      "e_score": 72.06,
      "e_to_par": 2.06,
      "p10": 68.22,
      "p90": 76.41,
      "sd": 3.26,
      "n_eff": 50.2
    },
    {
      "player_id": "sam_burns",
      "player_name": "Sam Burns",
      "wave": "all",
      "e_score": 72.09,
      "e_to_par": 2.09,
      "p10": 68.02,
      "p90": 76.76,
      "sd": 3.46,
      "n_eff": 62.3
    },
    {
      "player_id": "rory_mcilroy",
      "player_name": "Rory McIlroy",
      "wave": "all",
      "e_score": 72.14,
      "e_to_par": 2.14,
      "p10": 68.01,
      "p90": 76.83,
      "sd": 3.51,
      "n_eff": 37.5
    },
    {
      "player_id": "tommy_fleetwood",
      "player_name": "Tommy Fleetwood",
      "wave": "all",
      "e_score": 72.16,
      "e_to_par": 2.16,
      "p10": 68.22,
      "p90": 76.62,
      "sd": 3.34,
      "n_eff": 53.7
    },
    {
      "player_id": "collin_morikawa",
      "player_name": "Collin Morikawa",
      "wave": "all",
      "e_score": 72.27,
      "e_to_par": 2.27,
      "p10": 68.14,
      "p90": 77.06,
      "sd": 3.51,
      "n_eff": 47.7
    },
    {
      "player_id": "alex_fitzpatrick",
      "player_name": "Alex Fitzpatrick",
      "wave": "all",
      "e_score": 72.36,
      "e_to_par": 2.36,
      "p10": 68.33,
      "p90": 77.11,
      "sd": 3.46,
      "n_eff": 20.9
    },
    {
      "player_id": "keith_mitchell",
      "player_name": "Keith Mitchell",
      "wave": "all",
      "e_score": 72.36,
      "e_to_par": 2.36,
      "p10": 68.21,
      "p90": 77.11,
      "sd": 3.55,
      "n_eff": 62.2
    },
    {
      "player_id": "sahith_theegala",
      "player_name": "Sahith Theegala",
      "wave": "all",
      "e_score": 72.43,
      "e_to_par": 2.43,
      "p10": 68.19,
      "p90": 77.27,
      "sd": 3.59,
      "n_eff": 67.5
    },
    {
      "player_id": "tom_kim",
      "player_name": "Tom Kim",
      "wave": "all",
      "e_score": 72.45,
      "e_to_par": 2.45,
      "p10": 68.55,
      "p90": 76.91,
      "sd": 3.29,
      "n_eff": 57.5
    },
    {
      "player_id": "cameron_young",
      "player_name": "Cameron Young",
      "wave": "all",
      "e_score": 72.48,
      "e_to_par": 2.48,
      "p10": 68.21,
      "p90": 77.47,
      "sd": 3.63,
      "n_eff": 57.9
    },
    {
      "player_id": "tyrrell_hatton",
      "player_name": "Tyrrell Hatton",
      "wave": "all",
      "e_score": 72.49,
      "e_to_par": 2.49,
      "p10": 68.27,
      "p90": 77.36,
      "sd": 3.6,
      "n_eff": 11.2
    },
    {
      "player_id": "maverick_mcnealy",
      "player_name": "Maverick McNealy",
      "wave": "all",
      "e_score": 72.52,
      "e_to_par": 2.52,
      "p10": 68.47,
      "p90": 77.19,
      "sd": 3.42,
      "n_eff": 61.4
    },
    {
      "player_id": "sam_stevens",
      "player_name": "Sam Stevens",
      "wave": "all",
      "e_score": 72.53,
      "e_to_par": 2.53,
      "p10": 68.4,
      "p90": 77.16,
      "sd": 3.46,
      "n_eff": 69.4
    },
    {
      "player_id": "ben_griffin",
      "player_name": "Ben Griffin",
      "wave": "all",
      "e_score": 72.54,
      "e_to_par": 2.54,
      "p10": 68.56,
      "p90": 77.13,
      "sd": 3.39,
      "n_eff": 65.4
    },
    {
      "player_id": "ryder_cowan",
      "player_name": "Ryder Cowan",
      "wave": "all",
      "e_score": 72.57,
      "e_to_par": 2.57,
      "p10": 68.77,
      "p90": 76.87,
      "sd": 3.2,
      "n_eff": 3.0
    },
    {
      "player_id": "emiliano_grillo",
      "player_name": "Emiliano Grillo",
      "wave": "all",
      "e_score": 72.61,
      "e_to_par": 2.61,
      "p10": 68.3,
      "p90": 77.6,
      "sd": 3.7,
      "n_eff": 58.8
    },
    {
      "player_id": "keegan_bradley",
      "player_name": "Keegan Bradley",
      "wave": "all",
      "e_score": 72.65,
      "e_to_par": 2.65,
      "p10": 68.61,
      "p90": 77.29,
      "sd": 3.47,
      "n_eff": 56.6
    },
    {
      "player_id": "aaron_rai",
      "player_name": "Aaron Rai",
      "wave": "all",
      "e_score": 72.72,
      "e_to_par": 2.72,
      "p10": 68.8,
      "p90": 77.25,
      "sd": 3.33,
      "n_eff": 46.9
    },
    {
      "player_id": "robert_macintyre",
      "player_name": "Robert MacIntyre",
      "wave": "all",
      "e_score": 72.85,
      "e_to_par": 2.85,
      "p10": 68.56,
      "p90": 77.77,
      "sd": 3.61,
      "n_eff": 59.1
    },
    {
      "player_id": "j_t_poston",
      "player_name": "J.T. Poston",
      "wave": "all",
      "e_score": 72.86,
      "e_to_par": 2.86,
      "p10": 68.69,
      "p90": 77.61,
      "sd": 3.51,
      "n_eff": 58.0
    },
    {
      "player_id": "akshay_bhatia",
      "player_name": "Akshay Bhatia",
      "wave": "all",
      "e_score": 72.87,
      "e_to_par": 2.87,
      "p10": 68.39,
      "p90": 78.01,
      "sd": 3.81,
      "n_eff": 57.6
    },
    {
      "player_id": "gary_woodland",
      "player_name": "Gary Woodland",
      "wave": "all",
      "e_score": 72.9,
      "e_to_par": 2.9,
      "p10": 68.82,
      "p90": 77.63,
      "sd": 3.5,
      "n_eff": 56.3
    },
    {
      "player_id": "corey_conners",
      "player_name": "Corey Conners",
      "wave": "all",
      "e_score": 72.91,
      "e_to_par": 2.91,
      "p10": 69.05,
      "p90": 77.33,
      "sd": 3.29,
      "n_eff": 59.1
    },
    {
      "player_id": "ludvig_berg",
      "player_name": "Ludvig \u00c5berg",
      "wave": "all",
      "e_score": 72.91,
      "e_to_par": 2.91,
      "p10": 68.62,
      "p90": 77.85,
      "sd": 3.66,
      "n_eff": 53.1
    },
    {
      "player_id": "justin_thomas",
      "player_name": "Justin Thomas",
      "wave": "all",
      "e_score": 72.93,
      "e_to_par": 2.93,
      "p10": 68.61,
      "p90": 77.91,
      "sd": 3.64,
      "n_eff": 49.8
    },
    {
      "player_id": "joaqu_n_niemann",
      "player_name": "Joaqu\u00edn Niemann",
      "wave": "all",
      "e_score": 72.94,
      "e_to_par": 2.94,
      "p10": 68.48,
      "p90": 78.02,
      "sd": 3.82,
      "n_eff": 9.0
    },
    {
      "player_id": "chris_gotterup",
      "player_name": "Chris Gotterup",
      "wave": "all",
      "e_score": 72.98,
      "e_to_par": 2.98,
      "p10": 68.81,
      "p90": 77.73,
      "sd": 3.53,
      "n_eff": 62.9
    },
    {
      "player_id": "jordan_spieth",
      "player_name": "Jordan Spieth",
      "wave": "all",
      "e_score": 73.01,
      "e_to_par": 3.01,
      "p10": 69.1,
      "p90": 77.51,
      "sd": 3.28,
      "n_eff": 59.1
    },
    {
      "player_id": "michael_kim",
      "player_name": "Michael Kim",
      "wave": "all",
      "e_score": 73.01,
      "e_to_par": 3.01,
      "p10": 68.71,
      "p90": 77.92,
      "sd": 3.65,
      "n_eff": 64.7
    },
    {
      "player_id": "pierceson_coody",
      "player_name": "Pierceson Coody",
      "wave": "all",
      "e_score": 73.02,
      "e_to_par": 3.02,
      "p10": 68.52,
      "p90": 78.14,
      "sd": 3.81,
      "n_eff": 58.0
    },
    {
      "player_id": "max_mcgreevy",
      "player_name": "Max McGreevy",
      "wave": "all",
      "e_score": 73.02,
      "e_to_par": 3.02,
      "p10": 69.12,
      "p90": 77.54,
      "sd": 3.32,
      "n_eff": 60.5
    },
    {
      "player_id": "john_parry",
      "player_name": "John Parry",
      "wave": "all",
      "e_score": 73.03,
      "e_to_par": 3.03,
      "p10": 69.24,
      "p90": 77.22,
      "sd": 3.18,
      "n_eff": 42.3
    },
    {
      "player_id": "zac_blair",
      "player_name": "Zac Blair",
      "wave": "all",
      "e_score": 73.04,
      "e_to_par": 3.04,
      "p10": 69.35,
      "p90": 77.27,
      "sd": 3.12,
      "n_eff": 36.7
    },
    {
      "player_id": "ryo_hisatsune",
      "player_name": "Ryo Hisatsune",
      "wave": "all",
      "e_score": 73.04,
      "e_to_par": 3.04,
      "p10": 68.69,
      "p90": 78.07,
      "sd": 3.69,
      "n_eff": 73.2
    },
    {
      "player_id": "viktor_hovland",
      "player_name": "Viktor Hovland",
      "wave": "all",
      "e_score": 73.04,
      "e_to_par": 3.04,
      "p10": 68.94,
      "p90": 77.76,
      "sd": 3.46,
      "n_eff": 48.1
    },
    {
      "player_id": "jon_rahm",
      "player_name": "Jon Rahm",
      "wave": "all",
      "e_score": 73.05,
      "e_to_par": 3.05,
      "p10": 68.66,
      "p90": 78.06,
      "sd": 3.72,
      "n_eff": 12.0
    },
    {
      "player_id": "justin_rose",
      "player_name": "Justin Rose",
      "wave": "all",
      "e_score": 73.05,
      "e_to_par": 3.05,
      "p10": 68.7,
      "p90": 78.02,
      "sd": 3.68,
      "n_eff": 47.4
    },
    {
      "player_id": "patrick_reed",
      "player_name": "Patrick Reed",
      "wave": "all",
      "e_score": 73.06,
      "e_to_par": 3.06,
      "p10": 69.29,
      "p90": 77.39,
      "sd": 3.18,
      "n_eff": 11.0
    },
    {
      "player_id": "jackson_koivun",
      "player_name": "Jackson Koivun",
      "wave": "all",
      "e_score": 73.08,
      "e_to_par": 3.08,
      "p10": 68.85,
      "p90": 78.08,
      "sd": 3.64,
      "n_eff": 9.2
    },
    {
      "player_id": "si_woo_kim",
      "player_name": "Si Woo Kim",
      "wave": "all",
      "e_score": 73.09,
      "e_to_par": 3.09,
      "p10": 68.67,
      "p90": 78.15,
      "sd": 3.71,
      "n_eff": 69.1
    },
    {
      "player_id": "dustin_johnson",
      "player_name": "Dustin Johnson",
      "wave": "all",
      "e_score": 73.1,
      "e_to_par": 3.1,
      "p10": 68.8,
      "p90": 78.02,
      "sd": 3.63,
      "n_eff": 11.7
    },
    {
      "player_id": "william_mouw",
      "player_name": "William Mouw",
      "wave": "all",
      "e_score": 73.12,
      "e_to_par": 3.12,
      "p10": 69.08,
      "p90": 77.73,
      "sd": 3.42,
      "n_eff": 50.2
    },
    {
      "player_id": "j_j_spaun",
      "player_name": "J.J. Spaun",
      "wave": "all",
      "e_score": 73.13,
      "e_to_par": 3.13,
      "p10": 68.9,
      "p90": 78.06,
      "sd": 3.6,
      "n_eff": 58.8
    },
    {
      "player_id": "niklas_n_rgaard",
      "player_name": "Niklas N\u00f8rgaard",
      "wave": "all",
      "e_score": 73.14,
      "e_to_par": 3.14,
      "p10": 69.17,
      "p90": 77.66,
      "sd": 3.38,
      "n_eff": 17.3
    },
    {
      "player_id": "sungjae_im",
      "player_name": "Sungjae Im",
      "wave": "all",
      "e_score": 73.14,
      "e_to_par": 3.14,
      "p10": 68.72,
      "p90": 78.22,
      "sd": 3.72,
      "n_eff": 55.3
    },
    {
      "player_id": "ben_kohles",
      "player_name": "Ben Kohles",
      "wave": "all",
      "e_score": 73.14,
      "e_to_par": 3.14,
      "p10": 69.52,
      "p90": 77.21,
      "sd": 3.04,
      "n_eff": 39.1
    },
    {
      "player_id": "patrick_cantlay",
      "player_name": "Patrick Cantlay",
      "wave": "all",
      "e_score": 73.16,
      "e_to_par": 3.16,
      "p10": 68.94,
      "p90": 78.01,
      "sd": 3.59,
      "n_eff": 49.1
    },
    {
      "player_id": "ryan_fox",
      "player_name": "Ryan Fox",
      "wave": "all",
      "e_score": 73.18,
      "e_to_par": 3.18,
      "p10": 69.34,
      "p90": 77.61,
      "sd": 3.3,
      "n_eff": 51.3
    },
    {
      "player_id": "bud_cauley",
      "player_name": "Bud Cauley",
      "wave": "all",
      "e_score": 73.22,
      "e_to_par": 3.22,
      "p10": 69.16,
      "p90": 77.81,
      "sd": 3.39,
      "n_eff": 61.2
    },
    {
      "player_id": "andrew_putnam",
      "player_name": "Andrew Putnam",
      "wave": "all",
      "e_score": 73.22,
      "e_to_par": 3.22,
      "p10": 69.2,
      "p90": 77.77,
      "sd": 3.39,
      "n_eff": 62.1
    },
    {
      "player_id": "brian_harman",
      "player_name": "Brian Harman",
      "wave": "all",
      "e_score": 73.23,
      "e_to_par": 3.23,
      "p10": 68.86,
      "p90": 78.14,
      "sd": 3.67,
      "n_eff": 62.7
    },
    {
      "player_id": "kurt_kitayama",
      "player_name": "Kurt Kitayama",
      "wave": "all",
      "e_score": 73.27,
      "e_to_par": 3.27,
      "p10": 68.79,
      "p90": 78.49,
      "sd": 3.8,
      "n_eff": 57.3
    },
    {
      "player_id": "michael_brennan",
      "player_name": "Michael Brennan",
      "wave": "all",
      "e_score": 73.31,
      "e_to_par": 3.31,
      "p10": 69.29,
      "p90": 77.93,
      "sd": 3.39,
      "n_eff": 44.7
    },
    {
      "player_id": "russell_henley",
      "player_name": "Russell Henley",
      "wave": "all",
      "e_score": 73.35,
      "e_to_par": 3.35,
      "p10": 69.08,
      "p90": 78.3,
      "sd": 3.67,
      "n_eff": 51.2
    },
    {
      "player_id": "harris_english",
      "player_name": "Harris English",
      "wave": "all",
      "e_score": 73.36,
      "e_to_par": 3.36,
      "p10": 69.7,
      "p90": 77.54,
      "sd": 3.11,
      "n_eff": 61.7
    },
    {
      "player_id": "laurie_canter",
      "player_name": "Laurie Canter",
      "wave": "all",
      "e_score": 73.36,
      "e_to_par": 3.36,
      "p10": 69.64,
      "p90": 77.65,
      "sd": 3.14,
      "n_eff": 6.6
    },
    {
      "player_id": "sudarshan_yellamaraju",
      "player_name": "Sudarshan Yellamaraju",
      "wave": "all",
      "e_score": 73.39,
      "e_to_par": 3.39,
      "p10": 69.36,
      "p90": 77.94,
      "sd": 3.37,
      "n_eff": 45.2
    },
    {
      "player_id": "nick_taylor",
      "player_name": "Nick Taylor",
      "wave": "all",
      "e_score": 73.4,
      "e_to_par": 3.4,
      "p10": 69.2,
      "p90": 78.23,
      "sd": 3.59,
      "n_eff": 63.7
    },
    {
      "player_id": "ryan_gerard",
      "player_name": "Ryan Gerard",
      "wave": "all",
      "e_score": 73.4,
      "e_to_par": 3.4,
      "p10": 69.21,
      "p90": 78.16,
      "sd": 3.53,
      "n_eff": 66.6
    },
    {
      "player_id": "jason_day",
      "player_name": "Jason Day",
      "wave": "all",
      "e_score": 73.41,
      "e_to_par": 3.41,
      "p10": 68.82,
      "p90": 78.61,
      "sd": 3.87,
      "n_eff": 45.8
    },
    {
      "player_id": "jacob_bridgeman",
      "player_name": "Jacob Bridgeman",
      "wave": "all",
      "e_score": 73.43,
      "e_to_par": 3.43,
      "p10": 68.98,
      "p90": 78.57,
      "sd": 3.79,
      "n_eff": 66.0
    },
    {
      "player_id": "jake_knapp",
      "player_name": "Jake Knapp",
      "wave": "all",
      "e_score": 73.44,
      "e_to_par": 3.44,
      "p10": 69.1,
      "p90": 78.46,
      "sd": 3.69,
      "n_eff": 38.9
    },
    {
      "player_id": "adam_scott",
      "player_name": "Adam Scott",
      "wave": "all",
      "e_score": 73.46,
      "e_to_par": 3.46,
      "p10": 68.97,
      "p90": 78.67,
      "sd": 3.82,
      "n_eff": 48.4
    },
    {
      "player_id": "rickie_fowler",
      "player_name": "Rickie Fowler",
      "wave": "all",
      "e_score": 73.46,
      "e_to_par": 3.46,
      "p10": 68.77,
      "p90": 78.82,
      "sd": 3.98,
      "n_eff": 52.8
    },
    {
      "player_id": "max_greyserman",
      "player_name": "Max Greyserman",
      "wave": "all",
      "e_score": 73.5,
      "e_to_par": 3.5,
      "p10": 68.84,
      "p90": 78.76,
      "sd": 3.98,
      "n_eff": 56.6
    },
    {
      "player_id": "alex_noren",
      "player_name": "Alex Noren",
      "wave": "all",
      "e_score": 73.51,
      "e_to_par": 3.51,
      "p10": 69.5,
      "p90": 78.22,
      "sd": 3.43,
      "n_eff": 50.8
    },
    {
      "player_id": "hideki_matsuyama",
      "player_name": "Hideki Matsuyama",
      "wave": "all",
      "e_score": 73.53,
      "e_to_par": 3.53,
      "p10": 69.23,
      "p90": 78.46,
      "sd": 3.67,
      "n_eff": 63.4
    },
    {
      "player_id": "miles_russell",
      "player_name": "Miles Russell",
      "wave": "all",
      "e_score": 73.54,
      "e_to_par": 3.54,
      "p10": 69.85,
      "p90": 77.74,
      "sd": 3.09,
      "n_eff": 6.7
    },
    {
      "player_id": "ben_james",
      "player_name": "Ben James",
      "wave": "all",
      "e_score": 73.55,
      "e_to_par": 3.55,
      "p10": 68.56,
      "p90": 79.24,
      "sd": 4.23,
      "n_eff": 8.5
    },
    {
      "player_id": "jackson_van_paris",
      "player_name": "Jackson Van Paris",
      "wave": "all",
      "e_score": 73.55,
      "e_to_par": 3.55,
      "p10": 69.5,
      "p90": 78.18,
      "sd": 3.44,
      "n_eff": 4.8
    },
    {
      "player_id": "angel_hidalgo",
      "player_name": "Angel Hidalgo",
      "wave": "all",
      "e_score": 73.55,
      "e_to_par": 3.55,
      "p10": 69.75,
      "p90": 77.93,
      "sd": 3.27,
      "n_eff": 4.0
    },
    {
      "player_id": "spencer_tibbits",
      "player_name": "Spencer Tibbits",
      "wave": "all",
      "e_score": 73.58,
      "e_to_par": 3.58,
      "p10": 69.33,
      "p90": 78.39,
      "sd": 3.56,
      "n_eff": 3.0
    },
    {
      "player_id": "kristoffer_reitan",
      "player_name": "Kristoffer Reitan",
      "wave": "all",
      "e_score": 73.58,
      "e_to_par": 3.58,
      "p10": 69.25,
      "p90": 78.62,
      "sd": 3.66,
      "n_eff": 41.3
    },
    {
      "player_id": "bryson_dechambeau",
      "player_name": "Bryson DeChambeau",
      "wave": "all",
      "e_score": 73.59,
      "e_to_par": 3.59,
      "p10": 69.31,
      "p90": 78.6,
      "sd": 3.71,
      "n_eff": 8.4
    },
    {
      "player_id": "min_woo_lee",
      "player_name": "Min Woo Lee",
      "wave": "all",
      "e_score": 73.61,
      "e_to_par": 3.61,
      "p10": 69.1,
      "p90": 78.81,
      "sd": 3.86,
      "n_eff": 50.0
    },
    {
      "player_id": "marek_fleming",
      "player_name": "Marek Fleming",
      "wave": "all",
      "e_score": 73.62,
      "e_to_par": 3.62,
      "p10": 70.01,
      "p90": 77.74,
      "sd": 3.06,
      "n_eff": 3.0
    },
    {
      "player_id": "brooks_koepka",
      "player_name": "Brooks Koepka",
      "wave": "all",
      "e_score": 73.67,
      "e_to_par": 3.67,
      "p10": 69.24,
      "p90": 78.77,
      "sd": 3.74,
      "n_eff": 33.3
    },
    {
      "player_id": "shane_lowry",
      "player_name": "Shane Lowry",
      "wave": "all",
      "e_score": 73.67,
      "e_to_par": 3.67,
      "p10": 69.44,
      "p90": 78.58,
      "sd": 3.62,
      "n_eff": 49.7
    },
    {
      "player_id": "jackson_suber",
      "player_name": "Jackson Suber",
      "wave": "all",
      "e_score": 73.69,
      "e_to_par": 3.69,
      "p10": 68.91,
      "p90": 79.17,
      "sd": 4.02,
      "n_eff": 49.6
    },
    {
      "player_id": "johnny_keefer",
      "player_name": "Johnny Keefer",
      "wave": "all",
      "e_score": 73.7,
      "e_to_par": 3.7,
      "p10": 69.06,
      "p90": 79.03,
      "sd": 3.97,
      "n_eff": 47.1
    },
    {
      "player_id": "carlos_ortiz",
      "player_name": "Carlos Ortiz",
      "wave": "all",
      "e_score": 73.7,
      "e_to_par": 3.7,
      "p10": 69.72,
      "p90": 78.21,
      "sd": 3.35,
      "n_eff": 5.0
    },
    {
      "player_id": "andrew_novak",
      "player_name": "Andrew Novak",
      "wave": "all",
      "e_score": 73.71,
      "e_to_par": 3.71,
      "p10": 69.32,
      "p90": 78.86,
      "sd": 3.78,
      "n_eff": 62.8
    },
    {
      "player_id": "adrien_dumont_de_chassart",
      "player_name": "Adrien Dumont de Chassart",
      "wave": "all",
      "e_score": 73.71,
      "e_to_par": 3.71,
      "p10": 69.8,
      "p90": 78.15,
      "sd": 3.34,
      "n_eff": 34.4
    },
    {
      "player_id": "filippo_celli",
      "player_name": "Filippo Celli",
      "wave": "all",
      "e_score": 73.72,
      "e_to_par": 3.72,
      "p10": 69.69,
      "p90": 78.41,
      "sd": 3.44,
      "n_eff": 2.0
    },
    {
      "player_id": "cameron_smith",
      "player_name": "Cameron Smith",
      "wave": "all",
      "e_score": 73.77,
      "e_to_par": 3.77,
      "p10": 69.74,
      "p90": 78.37,
      "sd": 3.41,
      "n_eff": 8.7
    },
    {
      "player_id": "harry_higgs",
      "player_name": "Harry Higgs",
      "wave": "all",
      "e_score": 73.77,
      "e_to_par": 3.77,
      "p10": 69.48,
      "p90": 78.66,
      "sd": 3.62,
      "n_eff": 32.4
    },
    {
      "player_id": "nicolai_h_jgaard",
      "player_name": "Nicolai H\u00f8jgaard",
      "wave": "all",
      "e_score": 73.78,
      "e_to_par": 3.78,
      "p10": 69.44,
      "p90": 78.72,
      "sd": 3.65,
      "n_eff": 50.3
    },
    {
      "player_id": "alex_smalley",
      "player_name": "Alex Smalley",
      "wave": "all",
      "e_score": 73.79,
      "e_to_par": 3.79,
      "p10": 69.55,
      "p90": 78.71,
      "sd": 3.65,
      "n_eff": 61.9
    },
    {
      "player_id": "caleb_surratt",
      "player_name": "Caleb Surratt",
      "wave": "all",
      "e_score": 73.8,
      "e_to_par": 3.8,
      "p10": 69.73,
      "p90": 78.43,
      "sd": 3.48,
      "n_eff": 3.0
    },
    {
      "player_id": "nathan_kimsey",
      "player_name": "Nathan Kimsey",
      "wave": "all",
      "e_score": 73.85,
      "e_to_par": 3.85,
      "p10": 69.76,
      "p90": 78.51,
      "sd": 3.48,
      "n_eff": 3.1
    },
    {
      "player_id": "matthew_jordan",
      "player_name": "Matthew Jordan",
      "wave": "all",
      "e_score": 73.87,
      "e_to_par": 3.87,
      "p10": 69.83,
      "p90": 78.5,
      "sd": 3.43,
      "n_eff": 4.7
    },
    {
      "player_id": "lucas_herbert",
      "player_name": "Lucas Herbert",
      "wave": "all",
      "e_score": 73.88,
      "e_to_par": 3.88,
      "p10": 70.21,
      "p90": 78.02,
      "sd": 3.07,
      "n_eff": 2.5
    },
    {
      "player_id": "nico_echavarria",
      "player_name": "Nico Echavarria",
      "wave": "all",
      "e_score": 73.88,
      "e_to_par": 3.88,
      "p10": 68.89,
      "p90": 79.65,
      "sd": 4.31,
      "n_eff": 61.2
    },
    {
      "player_id": "sepp_straka",
      "player_name": "Sepp Straka",
      "wave": "all",
      "e_score": 73.89,
      "e_to_par": 3.89,
      "p10": 69.18,
      "p90": 79.39,
      "sd": 4.0,
      "n_eff": 52.1
    },
    {
      "player_id": "jack_schoenberger",
      "player_name": "Jack Schoenberger",
      "wave": "all",
      "e_score": 73.9,
      "e_to_par": 3.9,
      "p10": 70.33,
      "p90": 78.01,
      "sd": 3.01,
      "n_eff": 2.0
    },
    {
      "player_id": "cole_hammer",
      "player_name": "Cole Hammer",
      "wave": "all",
      "e_score": 73.91,
      "e_to_par": 3.91,
      "p10": 69.89,
      "p90": 78.49,
      "sd": 3.39,
      "n_eff": 3.4
    },
    {
      "player_id": "chris_kirk",
      "player_name": "Chris Kirk",
      "wave": "all",
      "e_score": 73.91,
      "e_to_par": 3.91,
      "p10": 69.78,
      "p90": 78.58,
      "sd": 3.5,
      "n_eff": 48.2
    },
    {
      "player_id": "billy_horschel",
      "player_name": "Billy Horschel",
      "wave": "all",
      "e_score": 73.96,
      "e_to_par": 3.96,
      "p10": 69.78,
      "p90": 78.73,
      "sd": 3.51,
      "n_eff": 53.3
    },
    {
      "player_id": "jimmy_stanger",
      "player_name": "Jimmy Stanger",
      "wave": "all",
      "e_score": 73.98,
      "e_to_par": 3.98,
      "p10": 70.18,
      "p90": 78.25,
      "sd": 3.21,
      "n_eff": 26.6
    },
    {
      "player_id": "ben_silverman",
      "player_name": "Ben Silverman",
      "wave": "all",
      "e_score": 73.98,
      "e_to_par": 3.98,
      "p10": 69.97,
      "p90": 78.59,
      "sd": 3.39,
      "n_eff": 36.2
    },
    {
      "player_id": "brandon_wu",
      "player_name": "Brandon Wu",
      "wave": "all",
      "e_score": 74.0,
      "e_to_par": 4.0,
      "p10": 69.14,
      "p90": 79.67,
      "sd": 4.19,
      "n_eff": 4.4
    },
    {
      "player_id": "giuseppe_puebla",
      "player_name": "Giuseppe Puebla",
      "wave": "all",
      "e_score": 74.12,
      "e_to_par": 4.12,
      "p10": 70.39,
      "p90": 78.3,
      "sd": 3.11,
      "n_eff": 2.0
    },
    {
      "player_id": "davis_thompson",
      "player_name": "Davis Thompson",
      "wave": "all",
      "e_score": 74.12,
      "e_to_par": 4.12,
      "p10": 70.05,
      "p90": 78.71,
      "sd": 3.43,
      "n_eff": 54.6
    },
    {
      "player_id": "manav_shah",
      "player_name": "Manav Shah",
      "wave": "all",
      "e_score": 74.14,
      "e_to_par": 4.14,
      "p10": 70.45,
      "p90": 78.32,
      "sd": 3.1,
      "n_eff": 2.0
    },
    {
      "player_id": "david_puig",
      "player_name": "David Puig",
      "wave": "all",
      "e_score": 74.15,
      "e_to_par": 4.15,
      "p10": 69.99,
      "p90": 78.9,
      "sd": 3.53,
      "n_eff": 6.3
    },
    {
      "player_id": "harry_hall",
      "player_name": "Harry Hall",
      "wave": "all",
      "e_score": 74.22,
      "e_to_par": 4.22,
      "p10": 70.19,
      "p90": 78.87,
      "sd": 3.4,
      "n_eff": 59.7
    },
    {
      "player_id": "kevin_roy",
      "player_name": "Kevin Roy",
      "wave": "all",
      "e_score": 74.23,
      "e_to_par": 4.23,
      "p10": 69.77,
      "p90": 79.36,
      "sd": 3.78,
      "n_eff": 57.1
    },
    {
      "player_id": "patrick_rodgers",
      "player_name": "Patrick Rodgers",
      "wave": "all",
      "e_score": 74.26,
      "e_to_par": 4.26,
      "p10": 69.96,
      "p90": 79.18,
      "sd": 3.7,
      "n_eff": 73.0
    },
    {
      "player_id": "daniel_berger",
      "player_name": "Daniel Berger",
      "wave": "all",
      "e_score": 74.27,
      "e_to_par": 4.27,
      "p10": 69.73,
      "p90": 79.49,
      "sd": 3.85,
      "n_eff": 53.4
    },
    {
      "player_id": "eric_lee",
      "player_name": "Eric Lee",
      "wave": "all",
      "e_score": 74.29,
      "e_to_par": 4.29,
      "p10": 70.17,
      "p90": 79.06,
      "sd": 3.53,
      "n_eff": 3.0
    },
    {
      "player_id": "neal_shipley",
      "player_name": "Neal Shipley",
      "wave": "all",
      "e_score": 74.31,
      "e_to_par": 4.31,
      "p10": 70.43,
      "p90": 78.83,
      "sd": 3.3,
      "n_eff": 29.7
    },
    {
      "player_id": "bryan_lee",
      "player_name": "Bryan Lee",
      "wave": "all",
      "e_score": 74.35,
      "e_to_par": 4.35,
      "p10": 70.46,
      "p90": 78.73,
      "sd": 3.27,
      "n_eff": 2.5
    },
    {
      "player_id": "adrien_saddier",
      "player_name": "Adrien Saddier",
      "wave": "all",
      "e_score": 74.35,
      "e_to_par": 4.35,
      "p10": 70.41,
      "p90": 78.96,
      "sd": 3.35,
      "n_eff": 28.9
    },
    {
      "player_id": "ugo_coussaud",
      "player_name": "Ugo Coussaud",
      "wave": "all",
      "e_score": 74.41,
      "e_to_par": 4.41,
      "p10": 70.2,
      "p90": 79.2,
      "sd": 3.52,
      "n_eff": 3.0
    },
    {
      "player_id": "chandler_phillips",
      "player_name": "Chandler Phillips",
      "wave": "all",
      "e_score": 74.45,
      "e_to_par": 4.45,
      "p10": 70.2,
      "p90": 79.23,
      "sd": 3.66,
      "n_eff": 48.4
    },
    {
      "player_id": "taihei_sato",
      "player_name": "Taihei Sato",
      "wave": "all",
      "e_score": 74.47,
      "e_to_par": 4.47,
      "p10": 70.78,
      "p90": 78.65,
      "sd": 3.08,
      "n_eff": 2.0
    },
    {
      "player_id": "carl_yuan",
      "player_name": "Carl Yuan",
      "wave": "all",
      "e_score": 74.47,
      "e_to_par": 4.47,
      "p10": 70.42,
      "p90": 79.15,
      "sd": 3.48,
      "n_eff": 6.2
    },
    {
      "player_id": "kaito_onishi",
      "player_name": "Kaito Onishi",
      "wave": "all",
      "e_score": 74.5,
      "e_to_par": 4.5,
      "p10": 70.43,
      "p90": 79.16,
      "sd": 3.47,
      "n_eff": 17.6
    },
    {
      "player_id": "peter_uihlein",
      "player_name": "Peter Uihlein",
      "wave": "all",
      "e_score": 74.53,
      "e_to_par": 4.53,
      "p10": 70.2,
      "p90": 79.53,
      "sd": 3.68,
      "n_eff": 3.0
    },
    {
      "player_id": "j_b_holmes",
      "player_name": "J.B. Holmes",
      "wave": "all",
      "e_score": 74.57,
      "e_to_par": 4.57,
      "p10": 70.85,
      "p90": 78.78,
      "sd": 3.12,
      "n_eff": 2.5
    },
    {
      "player_id": "alejandro_tosti",
      "player_name": "Alejandro Tosti",
      "wave": "all",
      "e_score": 74.61,
      "e_to_par": 4.61,
      "p10": 70.41,
      "p90": 79.35,
      "sd": 3.59,
      "n_eff": 35.7
    },
    {
      "player_id": "marcelo_rozo",
      "player_name": "Marcelo Rozo",
      "wave": "all",
      "e_score": 74.64,
      "e_to_par": 4.64,
      "p10": 70.83,
      "p90": 78.99,
      "sd": 3.2,
      "n_eff": 25.6
    },
    {
      "player_id": "jackson_herrington",
      "player_name": "Jackson Herrington",
      "wave": "all",
      "e_score": 74.64,
      "e_to_par": 4.64,
      "p10": 71.27,
      "p90": 78.49,
      "sd": 2.88,
      "n_eff": 3.5
    },
    {
      "player_id": "ryuichi_oiwa",
      "player_name": "Ryuichi Oiwa",
      "wave": "all",
      "e_score": 74.65,
      "e_to_par": 4.65,
      "p10": 70.58,
      "p90": 79.38,
      "sd": 3.49,
      "n_eff": 2.0
    },
    {
      "player_id": "cooper_dossey",
      "player_name": "Cooper Dossey",
      "wave": "all",
      "e_score": 74.66,
      "e_to_par": 4.66,
      "p10": 69.95,
      "p90": 80.08,
      "sd": 4.0,
      "n_eff": 3.9
    },
    {
      "player_id": "dylan_wu",
      "player_name": "Dylan Wu",
      "wave": "all",
      "e_score": 74.69,
      "e_to_par": 4.69,
      "p10": 70.65,
      "p90": 79.29,
      "sd": 3.41,
      "n_eff": 40.7
    },
    {
      "player_id": "taylor_montgomery",
      "player_name": "Taylor Montgomery",
      "wave": "all",
      "e_score": 74.7,
      "e_to_par": 4.7,
      "p10": 70.53,
      "p90": 79.58,
      "sd": 3.56,
      "n_eff": 22.7
    },
    {
      "player_id": "matt_mccarty",
      "player_name": "Matt McCarty",
      "wave": "all",
      "e_score": 74.76,
      "e_to_par": 4.76,
      "p10": 69.81,
      "p90": 80.56,
      "sd": 4.23,
      "n_eff": 61.6
    },
    {
      "player_id": "mason_howell",
      "player_name": "Mason Howell",
      "wave": "all",
      "e_score": 74.76,
      "e_to_par": 4.76,
      "p10": 70.33,
      "p90": 79.83,
      "sd": 3.73,
      "n_eff": 9.8
    },
    {
      "player_id": "james_nicholas",
      "player_name": "James Nicholas",
      "wave": "all",
      "e_score": 74.79,
      "e_to_par": 4.79,
      "p10": 70.22,
      "p90": 80.08,
      "sd": 3.94,
      "n_eff": 3.9
    },
    {
      "player_id": "padraig_harrington",
      "player_name": "Padraig Harrington",
      "wave": "all",
      "e_score": 74.81,
      "e_to_par": 4.81,
      "p10": 70.76,
      "p90": 79.44,
      "sd": 3.43,
      "n_eff": 10.4
    },
    {
      "player_id": "preston_stout",
      "player_name": "Preston Stout",
      "wave": "all",
      "e_score": 74.82,
      "e_to_par": 4.82,
      "p10": 70.49,
      "p90": 79.76,
      "sd": 3.67,
      "n_eff": 4.3
    },
    {
      "player_id": "jake_peacock",
      "player_name": "Jake Peacock",
      "wave": "all",
      "e_score": 74.83,
      "e_to_par": 4.83,
      "p10": 70.59,
      "p90": 79.73,
      "sd": 3.61,
      "n_eff": 4.7
    },
    {
      "player_id": "hamilton_coleman",
      "player_name": "Hamilton Coleman",
      "wave": "all",
      "e_score": 74.84,
      "e_to_par": 4.84,
      "p10": 70.39,
      "p90": 79.99,
      "sd": 3.84,
      "n_eff": 2.0
    },
    {
      "player_id": "jayden_schaper",
      "player_name": "Jayden Schaper",
      "wave": "all",
      "e_score": 74.88,
      "e_to_par": 4.88,
      "p10": 71.67,
      "p90": 78.52,
      "sd": 2.72,
      "n_eff": 3.7
    },
    {
      "player_id": "logan_reilly",
      "player_name": "Logan Reilly",
      "wave": "all",
      "e_score": 74.9,
      "e_to_par": 4.9,
      "p10": 70.64,
      "p90": 79.72,
      "sd": 3.56,
      "n_eff": 2.0
    },
    {
      "player_id": "graeme_mcdowell",
      "player_name": "Graeme McDowell",
      "wave": "all",
      "e_score": 75.01,
      "e_to_par": 5.01,
      "p10": 71.38,
      "p90": 79.06,
      "sd": 3.03,
      "n_eff": 2.0
    },
    {
      "player_id": "hennie_du_plessis",
      "player_name": "Hennie Du Plessis",
      "wave": "all",
      "e_score": 75.01,
      "e_to_par": 5.01,
      "p10": 71.41,
      "p90": 79.15,
      "sd": 3.07,
      "n_eff": 2.0
    },
    {
      "player_id": "matti_schmid",
      "player_name": "Matti Schmid",
      "wave": "all",
      "e_score": 75.01,
      "e_to_par": 5.01,
      "p10": 70.65,
      "p90": 79.98,
      "sd": 3.71,
      "n_eff": 56.4
    },
    {
      "player_id": "ethan_fang",
      "player_name": "Ethan Fang",
      "wave": "all",
      "e_score": 75.05,
      "e_to_par": 5.05,
      "p10": 71.2,
      "p90": 79.43,
      "sd": 3.27,
      "n_eff": 4.7
    },
    {
      "player_id": "chase_kyes",
      "player_name": "Chase Kyes",
      "wave": "all",
      "e_score": 75.05,
      "e_to_par": 5.05,
      "p10": 71.27,
      "p90": 79.5,
      "sd": 3.2,
      "n_eff": 2.0
    },
    {
      "player_id": "vaughn_harber",
      "player_name": "Vaughn Harber",
      "wave": "all",
      "e_score": 75.06,
      "e_to_par": 5.06,
      "p10": 71.32,
      "p90": 79.31,
      "sd": 3.16,
      "n_eff": 2.0
    },
    {
      "player_id": "brandon_holtz",
      "player_name": "Brandon Holtz",
      "wave": "all",
      "e_score": 75.11,
      "e_to_par": 5.11,
      "p10": 71.32,
      "p90": 79.43,
      "sd": 3.2,
      "n_eff": 3.5
    },
    {
      "player_id": "nick_hardy",
      "player_name": "Nick Hardy",
      "wave": "all",
      "e_score": 75.16,
      "e_to_par": 5.16,
      "p10": 70.92,
      "p90": 80.06,
      "sd": 3.57,
      "n_eff": 26.4
    },
    {
      "player_id": "mateo_pulcini",
      "player_name": "Mateo Pulcini",
      "wave": "all",
      "e_score": 75.29,
      "e_to_par": 5.29,
      "p10": 71.55,
      "p90": 79.6,
      "sd": 3.19,
      "n_eff": 3.5
    },
    {
      "player_id": "jake_sollon",
      "player_name": "Jake Sollon",
      "wave": "all",
      "e_score": 75.31,
      "e_to_par": 5.31,
      "p10": 70.65,
      "p90": 80.61,
      "sd": 3.95,
      "n_eff": 3.9
    },
    {
      "player_id": "t_k_kim",
      "player_name": "T.K. Kim",
      "wave": "all",
      "e_score": 75.74,
      "e_to_par": 5.74,
      "p10": 71.99,
      "p90": 79.98,
      "sd": 3.14,
      "n_eff": 2.0
    },
    {
      "player_id": "matthew_robles",
      "player_name": "Matthew Robles",
      "wave": "all",
      "e_score": 75.78,
      "e_to_par": 5.78,
      "p10": 72.04,
      "p90": 80.14,
      "sd": 3.19,
      "n_eff": 2.0
    },
    {
      "player_id": "rocco_repetto_taylor",
      "player_name": "Rocco Repetto Taylor",
      "wave": "all",
      "e_score": 75.97,
      "e_to_par": 5.97,
      "p10": 71.97,
      "p90": 80.65,
      "sd": 3.39,
      "n_eff": 2.0
    },
    {
      "player_id": "robbie_higgins",
      "player_name": "Robbie Higgins",
      "wave": "all",
      "e_score": 76.14,
      "e_to_par": 6.14,
      "p10": 71.25,
      "p90": 81.72,
      "sd": 4.11,
      "n_eff": 3.9
    },
    {
      "player_id": "jackson_ormond",
      "player_name": "Jackson Ormond",
      "wave": "all",
      "e_score": 76.48,
      "e_to_par": 6.48,
      "p10": 72.97,
      "p90": 80.47,
      "sd": 2.99,
      "n_eff": 2.0
    },
    {
      "player_id": "arni_sveinsson",
      "player_name": "Arni Sveinsson",
      "wave": "all",
      "e_score": 76.67,
      "e_to_par": 6.67,
      "p10": 72.5,
      "p90": 81.46,
      "sd": 3.53,
      "n_eff": 2.0
    },
    {
      "player_id": "greyson_leach",
      "player_name": "Greyson Leach",
      "wave": "all",
      "e_score": 76.68,
      "e_to_par": 6.68,
      "p10": 71.99,
      "p90": 81.86,
      "sd": 3.92,
      "n_eff": 3.9
    }
  ]
}